{"R":["#5e0a00","#820014","#7a101c","#631717","#d20004","#c70509","#d30d35","#ff4d51","#b23660","#f4a6ba","#fff9fa","#ffffff","#f0a8b0","#90504c","#fffdfe","#ffffff","#ece4e5"],"O":["#130b07","#693b19","#903a18","#2b2119","#ff730f","#291f19","#b94523","#e45a20","#fe734e","#ffd899","#df845d","#fff8f5","#ffffff","#f8c6b4","#b25c46","#ffffff","#f8f0ec","#c6ab90","#d2b8a4","#6b5f51","#f3eee9","#f7f4f3","#f4f2f0"],"Y":["#ffffff","#ecd9ac","#f4ebd4","#fcfdf7","#c8bb88","#a69e6e","#eeebd8"],"G":["#25290d","#1a2c10","#008214","#038d5d","#00da3c","#20441c","#00f4a0","#285c28","#25311f","#33792f","#9affd5","#98e35f","#cefcc4","#ffffff","#151917","#b5e18f","#83ad51","#578f77","#80b89f","#32342c","#76aa76","#c6e2ce","#c6dcd0","#c7d5c7"],"B":["#043838","#07133b","#095d5b","#12404c","#0e7e78","#0650a8","#064ea8","#007ad2","#1b397d","#227a9a","#29c1f7","#1a78ea","#2fdce9","#66dbfe","#68dafe","#2b6153","#2c8adc","#3978d3","#49a1d5","#bffdf1","#76aad6","#487a8e","#c9f3f1","#86a9d2","#e9f2f9","#dee8f2","#82b6b0","#abbdd3","#85b5b7","#8594ad","#ffffff","#ecf4f1","#87a9a5","#a7bcc3","#677383","#d1d9e1","#d0d8e0","#72708a","#e7eded","#ffffff"],"V":["#3c0256","#2a1874","#39238f","#501ae0","#4e38c2","#7163c5","#675581","#9a76b0","#c0becc"],"M":["#e605ff","#e90989","#cd6fbe","#b4568b","#f2dee6"]}